naaf/__init__.py
naaf/_version.py
naaf/cli.py
naaf/conftest.py
naaf/reading/__init__.py
naaf/reading/box.py
naaf/reading/cbox.py
naaf/reading/em.py
naaf/reading/main.py
naaf/reading/mrc.py
naaf/reading/star.py
naaf/reading/tbl.py
naaf/reading/_tests/__init__.py
naaf/reading/_tests/test_read.py
naaf/reading/_tests/test_read_em.py
naaf/reading/_tests/test_read_mrc.py
naaf/reading/_tests/test_read_star.py
naaf/reading/_tests/test_read_tbl.py
naaf/utils/__init__.py
naaf/utils/constants.py
naaf/utils/generic.py
naaf/utils/testing.py
naaf/writing/__init__.py
naaf/writing/em.py
naaf/writing/mrc.py
naaf/writing/star.py
naaf/writing/tbl.py
naaf/writing/_tests/__init__.py
naaf/writing/_tests/test_write_em.py
naaf/writing/_tests/test_write_mrc.py
naaf/writing/_tests/test_write_star.py
naaf/writing/_tests/test_write_tbl.py
naaf-0.3.1.dist-info/LICENSE
naaf-0.3.1.dist-info/METADATA
naaf-0.3.1.dist-info/WHEEL
naaf-0.3.1.dist-info/entry_points.txt
naaf-0.3.1.dist-info/top_level.txt
naaf-0.3.1.dist-info/RECORD
