Metadata-Version: 2.1
Name: naaf
Version: 0.3.1
Summary: IO hub for Cryo-EM, Cryo-ET and subtomogram averaging data.
Home-page: https://github.com/gutsche-lab/naaf
Download-URL: https://github.com/gutsche-lab/naaf
Author: Blik Team
Author-email: blik-team@googlegroups.com
License: GNU General Public License v3 (GPLv3)
Project-URL: Bug Tracker, https://github.com/gutsche-lab/naaf/issues
Project-URL: Documentation, https://github.com/gutsche-lab/naaf#README.md
Project-URL: Source Code, https://github.com/gutsche-lab/naaf
Project-URL: Changelog, https://github.com/gutsche-lab/naaf/blob/main/CHANGELOG.md
Classifier: Development Status :: 2 - Pre-Alpha
Classifier: Environment :: X11 Applications :: Qt
Classifier: Intended Audience :: Education
Classifier: Intended Audience :: Science/Research
Classifier: License :: OSI Approved :: GNU General Public License v3 (GPLv3)
Classifier: Programming Language :: Python
Classifier: Programming Language :: Python :: 3 :: Only
Classifier: Programming Language :: Python :: 3.8
Classifier: Programming Language :: Python :: 3.9
Classifier: Programming Language :: Python :: 3.10
Classifier: Topic :: Scientific/Engineering
Classifier: Topic :: Scientific/Engineering :: Visualization
Classifier: Topic :: Scientific/Engineering :: Information Analysis
Classifier: Topic :: Scientific/Engineering :: Bio-Informatics
Classifier: Topic :: Utilities
Requires-Python: >=3.8
License-File: LICENSE
Requires-Dist: numpy
Requires-Dist: pandas
Requires-Dist: scipy
Requires-Dist: dask
Requires-Dist: click
Requires-Dist: pydantic
Requires-Dist: ipython
Requires-Dist: cryotypes
Requires-Dist: dynamotable (==0.2.4)
Requires-Dist: mrcfile (==1.3.0)
Requires-Dist: starfile (==0.4.5)
Requires-Dist: emfile (==0.3)
Provides-Extra: dev
Requires-Dist: tox ; extra == 'dev'
Requires-Dist: pytest ; extra == 'dev'
Requires-Dist: pytest-cov ; extra == 'dev'
Requires-Dist: ipython ; extra == 'dev'
Requires-Dist: black ; extra == 'dev'
Requires-Dist: flake8 ; extra == 'dev'
Requires-Dist: isort ; extra == 'dev'
Requires-Dist: pre-commit ; extra == 'dev'
